<?xml version = '1.0' encoding = 'UTF-8'?>
<TableProxyOraclev11g class="oracle.dbtools.crest.model.design.storage.oracle.v11g.TableProxyOraclev11g" name="AR_RMA_RCPT" directorySegmentName="seg_0" id="45386BF7-B528-5B3A-2B28-DAC3A2E8F1A0">
<createdBy>jjs</createdBy>
<createdTime>2020-01-25 14:09:24 UTC</createdTime>
<ownerDesignName>aerodemo_sqldeveloper_model</ownerDesignName>
<schemaObject>807C085E-39F3-5B40-6ED5-D061A11064F8</schemaObject>
<logging>YES</logging>
<partitionedRowMovement>DISABLE</partitionedRowMovement>
<segment>93EC1EBB-23A8-C18D-0AD1-DA5567D648D8</segment>
<tableSpace>2F79DF2C-B330-1435-F3B7-ADD6FC3016F1</tableSpace>
<temporaryChanged>false</temporaryChanged>
<accessDriverType>oracle_loader</accessDriverType>
<rejectLimit></rejectLimit>
<columnProxies itemClass="oracle.dbtools.crest.model.design.storage.oracle.v12c.ColumnProxyOraclev12c">
<ColumnProxy name="UT_USER_NBR_INSPECT" id="02F21F94-C366-9B78-B09A-AB887F14838A">
<createdBy>jjs</createdBy>
<createdTime>2020-01-25 14:09:25 UTC</createdTime>
<ownerDesignName>aerodemo_sqldeveloper_model</ownerDesignName>
</ColumnProxy>
<ColumnProxy name="BIN_NBR_STAGE" id="0541DECC-9730-F659-B9D8-72FE0149CF0C">
<createdBy>jjs</createdBy>
<createdTime>2020-01-25 14:09:25 UTC</createdTime>
<ownerDesignName>aerodemo_sqldeveloper_model</ownerDesignName>
</ColumnProxy>
<ColumnProxy name="RCPT_STAT_ID" id="13492BA3-2A2E-443A-277B-B29235BAA923">
<createdBy>jjs</createdBy>
<createdTime>2020-01-25 14:09:25 UTC</createdTime>
<ownerDesignName>aerodemo_sqldeveloper_model</ownerDesignName>
</ColumnProxy>
<ColumnProxy name="QTY_RECEIVED" id="1F4B58C8-F11D-EFB1-3FC5-13C0645B422E">
<createdBy>jjs</createdBy>
<createdTime>2020-01-25 14:09:25 UTC</createdTime>
<ownerDesignName>aerodemo_sqldeveloper_model</ownerDesignName>
</ColumnProxy>
<ColumnProxy name="UT_USER_NBR" id="2494050C-8E84-0FB7-8368-A4185F7D3938">
<createdBy>jjs</createdBy>
<createdTime>2020-01-25 14:09:25 UTC</createdTime>
<ownerDesignName>aerodemo_sqldeveloper_model</ownerDesignName>
</ColumnProxy>
<ColumnProxy name="PROCESS_DT" id="2FA68776-5D53-61A4-05C0-5A6253505300">
<createdBy>jjs</createdBy>
<createdTime>2020-01-25 14:09:25 UTC</createdTime>
<ownerDesignName>aerodemo_sqldeveloper_model</ownerDesignName>
</ColumnProxy>
<ColumnProxy name="QTY_ACCEPTED_STK_UM" id="30209645-4ECB-FB23-D145-1A89E0C46883">
<createdBy>jjs</createdBy>
<createdTime>2020-01-25 14:09:25 UTC</createdTime>
<ownerDesignName>aerodemo_sqldeveloper_model</ownerDesignName>
</ColumnProxy>
<ColumnProxy name="QTY_RECEIVED_STK_UM" id="3D519BD6-2D84-4598-3B61-2844E5A2A384">
<createdBy>jjs</createdBy>
<createdTime>2020-01-25 14:09:25 UTC</createdTime>
<ownerDesignName>aerodemo_sqldeveloper_model</ownerDesignName>
</ColumnProxy>
<ColumnProxy name="ORG_NBR_CUST" id="534477BE-2618-21D5-CB7F-644FB70A961A">
<createdBy>jjs</createdBy>
<createdTime>2020-01-25 14:09:25 UTC</createdTime>
<ownerDesignName>aerodemo_sqldeveloper_model</ownerDesignName>
</ColumnProxy>
<ColumnProxy name="QTY_ACCEPTED" id="58E3D990-AEE6-ED3F-6AD6-0E48C142EC51">
<createdBy>jjs</createdBy>
<createdTime>2020-01-25 14:09:25 UTC</createdTime>
<ownerDesignName>aerodemo_sqldeveloper_model</ownerDesignName>
</ColumnProxy>
<ColumnProxy name="FACILITY_RECV" id="5B05D4C3-C988-6B98-EC97-9F0E05138B0C">
<createdBy>jjs</createdBy>
<createdTime>2020-01-25 14:09:25 UTC</createdTime>
<ownerDesignName>aerodemo_sqldeveloper_model</ownerDesignName>
</ColumnProxy>
<ColumnProxy name="RMA_COMMENTS" id="658C1944-931F-9ABC-BC1F-BA977E47DC3D">
<createdBy>jjs</createdBy>
<createdTime>2020-01-25 14:09:25 UTC</createdTime>
<ownerDesignName>aerodemo_sqldeveloper_model</ownerDesignName>
</ColumnProxy>
<ColumnProxy name="IC_TRANS_GL_NBR" id="7735E9B4-A81A-240E-C1F2-D4C6C746814F">
<createdBy>jjs</createdBy>
<createdTime>2020-01-25 14:09:25 UTC</createdTime>
<ownerDesignName>aerodemo_sqldeveloper_model</ownerDesignName>
</ColumnProxy>
<ColumnProxy name="RCPT_DT" id="7DCA9F0B-AAC6-8E38-0EB7-BFCE56D4EA59">
<createdBy>jjs</createdBy>
<createdTime>2020-01-25 14:09:25 UTC</createdTime>
<ownerDesignName>aerodemo_sqldeveloper_model</ownerDesignName>
</ColumnProxy>
<ColumnProxy name="ITEM_NBR" id="A28C6A83-32C7-D214-84D5-550214E23FD4">
<createdBy>jjs</createdBy>
<createdTime>2020-01-25 14:09:25 UTC</createdTime>
<ownerDesignName>aerodemo_sqldeveloper_model</ownerDesignName>
</ColumnProxy>
<ColumnProxy name="AR_RMA_DTL_NBR" id="A81E60E1-0347-835B-A45E-D01F3DE360D9">
<createdBy>jjs</createdBy>
<createdTime>2020-01-25 14:09:25 UTC</createdTime>
<ownerDesignName>aerodemo_sqldeveloper_model</ownerDesignName>
</ColumnProxy>
<ColumnProxy name="AR_RMA_RCPT_NBR" id="B07F491B-FF15-D095-0DD2-830314F4E04A">
<createdBy>jjs</createdBy>
<createdTime>2020-01-25 14:09:25 UTC</createdTime>
<ownerDesignName>aerodemo_sqldeveloper_model</ownerDesignName>
</ColumnProxy>
<ColumnProxy name="UT_USER_NBR_RECV" id="B0F47A40-720E-EE07-474F-0CBD5A857965">
<createdBy>jjs</createdBy>
<createdTime>2020-01-25 14:09:25 UTC</createdTime>
<ownerDesignName>aerodemo_sqldeveloper_model</ownerDesignName>
</ColumnProxy>
<ColumnProxy name="LOT_NBR_RECV" id="B1F60748-C495-9236-13A1-5865354621B6">
<createdBy>jjs</createdBy>
<createdTime>2020-01-25 14:09:25 UTC</createdTime>
<ownerDesignName>aerodemo_sqldeveloper_model</ownerDesignName>
</ColumnProxy>
<ColumnProxy name="APS_SPLY_SUB_POOL_NBR_RECV" id="C1B64CBA-A5A8-DEE5-4A42-05BF4A89FE9D">
<createdBy>jjs</createdBy>
<createdTime>2020-01-25 14:09:25 UTC</createdTime>
<ownerDesignName>aerodemo_sqldeveloper_model</ownerDesignName>
</ColumnProxy>
<ColumnProxy name="LAST_MOD_DT" id="C4894D01-D00A-F10A-88E2-60C33630830B">
<createdBy>jjs</createdBy>
<createdTime>2020-01-25 14:09:25 UTC</createdTime>
<ownerDesignName>aerodemo_sqldeveloper_model</ownerDesignName>
</ColumnProxy>
<ColumnProxy name="RMA_UM" id="E8E07FEB-A330-A195-AFF8-FB8D7CA522B7">
<createdBy>jjs</createdBy>
<createdTime>2020-01-25 14:09:25 UTC</createdTime>
<ownerDesignName>aerodemo_sqldeveloper_model</ownerDesignName>
</ColumnProxy>
<ColumnProxy name="LOT_COST_LANDED" id="F46F20BD-90DB-3939-EF81-1D5B03C1EF6F">
<createdBy>jjs</createdBy>
<createdTime>2020-01-25 14:09:25 UTC</createdTime>
<ownerDesignName>aerodemo_sqldeveloper_model</ownerDesignName>
</ColumnProxy>
</columnProxies>
<indexProxies>
<IndexProxy class="oracle.dbtools.crest.model.design.storage.oracle.v10g.IndexProxyOraclev10g" name="AR_RMA_RCPT_NDX_01" id="156E0D33-30CF-604C-0551-94095DD63CC2">
<createdBy>jjs</createdBy>
<createdTime>2020-01-25 14:09:26 UTC</createdTime>
<ownerDesignName>aerodemo_sqldeveloper_model</ownerDesignName>
<schemaObject>807C085E-39F3-5B40-6ED5-D061A11064F8</schemaObject>
<segment>9707E8F8-BBA0-B136-AB67-6A0A1453A10B</segment>
<tableSpace>2F79DF2C-B330-1435-F3B7-ADD6FC3016F1</tableSpace>
</IndexProxy>
<IndexProxy class="oracle.dbtools.crest.model.design.storage.oracle.v10g.IndexProxyOraclev10g" name="AR_RMA_RCPT_PK" id="C9CBDD69-C34D-4276-5066-25373506AF08">
<createdBy>jjs</createdBy>
<createdTime>2020-01-25 14:09:26 UTC</createdTime>
<ownerDesignName>aerodemo_sqldeveloper_model</ownerDesignName>
<schemaObject>807C085E-39F3-5B40-6ED5-D061A11064F8</schemaObject>
<segment>9707E8F8-BBA0-B136-AB67-6A0A1453A10B</segment>
<tableSpace>2F79DF2C-B330-1435-F3B7-ADD6FC3016F1</tableSpace>
</IndexProxy>
</indexProxies>
<primaryKeys>
<PrimaryKey class="oracle.dbtools.crest.model.design.storage.oracle.v10g.PKProxyOraclev10g" name="AR_RMA_RCPT_PK" id="6E198DE7-3C9E-8A0C-BCEC-EE8CD409EE7C">
<createdBy>jjs</createdBy>
<createdTime>2020-01-25 14:09:27 UTC</createdTime>
<ownerDesignName>aerodemo_sqldeveloper_model</ownerDesignName>
<segment>9707E8F8-BBA0-B136-AB67-6A0A1453A10B</segment>
<tableSpace>2F79DF2C-B330-1435-F3B7-ADD6FC3016F1</tableSpace>
<existingIndex>C9CBDD69-C34D-4276-5066-25373506AF08</existingIndex>
<indexSegment>9707E8F8-BBA0-B136-AB67-6A0A1453A10B</indexSegment>
<indexSort>SORTED</indexSort>
<usingIndex>BY INDEX NAME</usingIndex>
</PrimaryKey>
</primaryKeys>
</TableProxyOraclev11g>